{
  "info": {
    "name": "E-Commerce Backend API",
    "description": "Complete API collection for the E-Commerce Backend",
    "schema": "https://schema.getpostman.com/json/collection/v2.1.0/collection.json",
    "version": "1.0.0"
  },
  "variable": [
    {
      "key": "baseUrl",
      "value": "http://localhost:3000",
      "type": "string"
    },
    {
      "key": "accessToken",
      "value": "",
      "type": "string"
    },
    {
      "key": "adminToken",
      "value": "",
      "type": "string"
    },
    {
      "key": "userId",
      "value": "",
      "type": "string"
    },
    {
      "key": "productId",
      "value": "",
      "type": "string"
    },
    {
      "key": "orderId",
      "value": "",
      "type": "string"
    }
  ],
  "item": [
    {
      "name": "Health",
      "item": [
        {
          "name": "Health Check",
          "request": {
            "method": "GET",
            "header": [],
            "url": {
              "raw": "{{baseUrl}}/health",
              "host": ["{{baseUrl}}"],
              "path": ["health"]
            }
          }
        },
        {
          "name": "Detailed Health Check",
          "request": {
            "method": "GET",
            "header": [],
            "url": {
              "raw": "{{baseUrl}}/health/detailed",
              "host": ["{{baseUrl}}"],
              "path": ["health", "detailed"]
            }
          }
        },
        {
          "name": "API Info",
          "request": {
            "method": "GET",
            "header": [],
            "url": {
              "raw": "{{baseUrl}}/api/info",
              "host": ["{{baseUrl}}"],
              "path": ["api", "info"]
            }
          }
        }
      ]
    },
    {
      "name": "Auth",
      "item": [
        {
          "name": "Register",
          "event": [
            {
              "listen": "test",
              "script": {
                "exec": [
                  "if (pm.response.code === 201) {",
                  "    var jsonData = pm.response.json();",
                  "    pm.collectionVariables.set('accessToken', jsonData.data.accessToken);",
                  "}"
                ]
              }
            }
          ],
          "request": {
            "method": "POST",
            "header": [
              {
                "key": "Content-Type",
                "value": "application/json"
              }
            ],
            "body": {
              "mode": "raw",
              "raw": "{\n  \"email\": \"user@example.com\",\n  \"password\": \"SecurePass123!\",\n  \"name\": \"John Doe\"\n}"
            },
            "url": {
              "raw": "{{baseUrl}}/auth/register",
              "host": ["{{baseUrl}}"],
              "path": ["auth", "register"]
            }
          }
        },
        {
          "name": "Login",
          "event": [
            {
              "listen": "test",
              "script": {
                "exec": [
                  "if (pm.response.code === 200) {",
                  "    var jsonData = pm.response.json();",
                  "    pm.collectionVariables.set('accessToken', jsonData.data.accessToken);",
                  "    pm.collectionVariables.set('userId', jsonData.data.user.id);",
                  "}"
                ]
              }
            }
          ],
          "request": {
            "method": "POST",
            "header": [
              {
                "key": "Content-Type",
                "value": "application/json"
              }
            ],
            "body": {
              "mode": "raw",
              "raw": "{\n  \"email\": \"user@example.com\",\n  \"password\": \"SecurePass123!\"\n}"
            },
            "url": {
              "raw": "{{baseUrl}}/auth/login",
              "host": ["{{baseUrl}}"],
              "path": ["auth", "login"]
            }
          }
        },
        {
          "name": "Get Current User",
          "request": {
            "method": "GET",
            "header": [
              {
                "key": "Authorization",
                "value": "Bearer {{accessToken}}"
              }
            ],
            "url": {
              "raw": "{{baseUrl}}/auth/me",
              "host": ["{{baseUrl}}"],
              "path": ["auth", "me"]
            }
          }
        },
        {
          "name": "Refresh Token",
          "request": {
            "method": "POST",
            "header": [],
            "url": {
              "raw": "{{baseUrl}}/auth/refresh",
              "host": ["{{baseUrl}}"],
              "path": ["auth", "refresh"]
            }
          }
        },
        {
          "name": "Logout",
          "request": {
            "method": "POST",
            "header": [
              {
                "key": "Authorization",
                "value": "Bearer {{accessToken}}"
              }
            ],
            "url": {
              "raw": "{{baseUrl}}/auth/logout",
              "host": ["{{baseUrl}}"],
              "path": ["auth", "logout"]
            }
          }
        }
      ]
    },
    {
      "name": "Products",
      "item": [
        {
          "name": "List Products",
          "request": {
            "method": "GET",
            "header": [],
            "url": {
              "raw": "{{baseUrl}}/products?page=1&limit=20",
              "host": ["{{baseUrl}}"],
              "path": ["products"],
              "query": [
                {
                  "key": "page",
                  "value": "1"
                },
                {
                  "key": "limit",
                  "value": "20"
                }
              ]
            }
          }
        },
        {
          "name": "Get Product by ID",
          "event": [
            {
              "listen": "test",
              "script": {
                "exec": [
                  "if (pm.response.code === 200) {",
                  "    var jsonData = pm.response.json();",
                  "    pm.collectionVariables.set('productId', jsonData.id);",
                  "}"
                ]
              }
            }
          ],
          "request": {
            "method": "GET",
            "header": [],
            "url": {
              "raw": "{{baseUrl}}/products/:id",
              "host": ["{{baseUrl}}"],
              "path": ["products", ":id"],
              "variable": [
                {
                  "key": "id",
                  "value": "{{productId}}"
                }
              ]
            }
          }
        },
        {
          "name": "Create Product (Admin)",
          "request": {
            "method": "POST",
            "header": [
              {
                "key": "Authorization",
                "value": "Bearer {{adminToken}}"
              },
              {
                "key": "Content-Type",
                "value": "application/json"
              }
            ],
            "body": {
              "mode": "raw",
              "raw": "{\n  \"slug\": \"new-product\",\n  \"title\": \"New Product\",\n  \"description\": \"Product description\",\n  \"variants\": [\n    {\n      \"sku\": \"SKU-001\",\n      \"price\": 29.99,\n      \"stock\": 100,\n      \"attributes\": {\n        \"size\": \"M\",\n        \"color\": \"Blue\"\n      }\n    }\n  ]\n}"
            },
            "url": {
              "raw": "{{baseUrl}}/products",
              "host": ["{{baseUrl}}"],
              "path": ["products"]
            }
          }
        }
      ]
    },
    {
      "name": "Orders",
      "item": [
        {
          "name": "Create Order",
          "event": [
            {
              "listen": "test",
              "script": {
                "exec": [
                  "if (pm.response.code === 201) {",
                  "    var jsonData = pm.response.json();",
                  "    pm.collectionVariables.set('orderId', jsonData.id);",
                  "}"
                ]
              }
            }
          ],
          "request": {
            "method": "POST",
            "header": [
              {
                "key": "Authorization",
                "value": "Bearer {{accessToken}}"
              },
              {
                "key": "Content-Type",
                "value": "application/json"
              }
            ],
            "body": {
              "mode": "raw",
              "raw": "{\n  \"userId\": \"{{userId}}\",\n  \"items\": [\n    {\n      \"sku\": \"SKU-001\",\n      \"quantity\": 2\n    }\n  ],\n  \"idempotencyKey\": \"unique-key-{{$timestamp}}\"\n}"
            },
            "url": {
              "raw": "{{baseUrl}}/orders",
              "host": ["{{baseUrl}}"],
              "path": ["orders"]
            }
          }
        },
        {
          "name": "Get User Orders",
          "request": {
            "method": "GET",
            "header": [
              {
                "key": "Authorization",
                "value": "Bearer {{accessToken}}"
              }
            ],
            "url": {
              "raw": "{{baseUrl}}/orders",
              "host": ["{{baseUrl}}"],
              "path": ["orders"]
            }
          }
        },
        {
          "name": "Get Order by ID",
          "request": {
            "method": "GET",
            "header": [
              {
                "key": "Authorization",
                "value": "Bearer {{accessToken}}"
              }
            ],
            "url": {
              "raw": "{{baseUrl}}/orders/:id",
              "host": ["{{baseUrl}}"],
              "path": ["orders", ":id"],
              "variable": [
                {
                  "key": "id",
                  "value": "{{orderId}}"
                }
              ]
            }
          }
        }
      ]
    },
    {
      "name": "Payments",
      "item": [
        {
          "name": "Create Payment Intent",
          "request": {
            "method": "POST",
            "header": [
              {
                "key": "Authorization",
                "value": "Bearer {{accessToken}}"
              },
              {
                "key": "Content-Type",
                "value": "application/json"
              }
            ],
            "body": {
              "mode": "raw",
              "raw": "{\n  \"orderId\": \"{{orderId}}\",\n  \"amount\": 59.98,\n  \"currency\": \"USD\"\n}"
            },
            "url": {
              "raw": "{{baseUrl}}/payments/intent",
              "host": ["{{baseUrl}}"],
              "path": ["payments", "intent"]
            }
          }
        },
        {
          "name": "Confirm Payment",
          "request": {
            "method": "POST",
            "header": [
              {
                "key": "Authorization",
                "value": "Bearer {{accessToken}}"
              },
              {
                "key": "Content-Type",
                "value": "application/json"
              }
            ],
            "body": {
              "mode": "raw",
              "raw": "{\n  \"paymentIntentId\": \"pi_xxx\",\n  \"orderId\": \"{{orderId}}\"\n}"
            },
            "url": {
              "raw": "{{baseUrl}}/payments/confirm",
              "host": ["{{baseUrl}}"],
              "path": ["payments", "confirm"]
            }
          }
        }
      ]
    },
    {
      "name": "Cart",
      "item": [
        {
          "name": "Add Item to Cart",
          "request": {
            "method": "POST",
            "header": [
              {
                "key": "Authorization",
                "value": "Bearer {{accessToken}}"
              },
              {
                "key": "Content-Type",
                "value": "application/json"
              }
            ],
            "body": {
              "mode": "raw",
              "raw": "{\n  \"sku\": \"SKU-001\",\n  \"quantity\": 2\n}"
            },
            "url": {
              "raw": "{{baseUrl}}/cart/items",
              "host": ["{{baseUrl}}"],
              "path": ["cart", "items"]
            }
          }
        },
        {
          "name": "Get Cart",
          "request": {
            "method": "GET",
            "header": [
              {
                "key": "Authorization",
                "value": "Bearer {{accessToken}}"
              }
            ],
            "url": {
              "raw": "{{baseUrl}}/cart",
              "host": ["{{baseUrl}}"],
              "path": ["cart"]
            }
          }
        },
        {
          "name": "Update Cart Item",
          "request": {
            "method": "PATCH",
            "header": [
              {
                "key": "Authorization",
                "value": "Bearer {{accessToken}}"
              },
              {
                "key": "Content-Type",
                "value": "application/json"
              }
            ],
            "body": {
              "mode": "raw",
              "raw": "{\n  \"quantity\": 3\n}"
            },
            "url": {
              "raw": "{{baseUrl}}/cart/items/:sku",
              "host": ["{{baseUrl}}"],
              "path": ["cart", "items", ":sku"],
              "variable": [
                {
                  "key": "sku",
                  "value": "SKU-001"
                }
              ]
            }
          }
        },
        {
          "name": "Clear Cart",
          "request": {
            "method": "DELETE",
            "header": [
              {
                "key": "Authorization",
                "value": "Bearer {{accessToken}}"
              }
            ],
            "url": {
              "raw": "{{baseUrl}}/cart",
              "host": ["{{baseUrl}}"],
              "path": ["cart"]
            }
          }
        }
      ]
    },
    {
      "name": "Search",
      "item": [
        {
          "name": "Search Products",
          "request": {
            "method": "GET",
            "header": [],
            "url": {
              "raw": "{{baseUrl}}/search?q=laptop&page=1&limit=20",
              "host": ["{{baseUrl}}"],
              "path": ["search"],
              "query": [
                {
                  "key": "q",
                  "value": "laptop"
                },
                {
                  "key": "page",
                  "value": "1"
                },
                {
                  "key": "limit",
                  "value": "20"
                }
              ]
            }
          }
        }
      ]
    },
    {
      "name": "Recommendations",
      "item": [
        {
          "name": "Get Product Recommendations",
          "request": {
            "method": "GET",
            "header": [
              {
                "key": "Authorization",
                "value": "Bearer {{accessToken}}"
              }
            ],
            "url": {
              "raw": "{{baseUrl}}/recommendations/product/:productId?limit=10",
              "host": ["{{baseUrl}}"],
              "path": ["recommendations", "product", ":productId"],
              "query": [
                {
                  "key": "limit",
                  "value": "10"
                }
              ],
              "variable": [
                {
                  "key": "productId",
                  "value": "{{productId}}"
                }
              ]
            }
          }
        }
      ]
    },
    {
      "name": "Reviews",
      "item": [
        {
          "name": "Create Review",
          "request": {
            "method": "POST",
            "header": [
              {
                "key": "Authorization",
                "value": "Bearer {{accessToken}}"
              },
              {
                "key": "Content-Type",
                "value": "application/json"
              }
            ],
            "body": {
              "mode": "raw",
              "raw": "{\n  \"productId\": \"{{productId}}\",\n  \"rating\": 5,\n  \"comment\": \"Great product!\"\n}"
            },
            "url": {
              "raw": "{{baseUrl}}/reviews",
              "host": ["{{baseUrl}}"],
              "path": ["reviews"]
            }
          }
        },
        {
          "name": "Get Product Reviews",
          "request": {
            "method": "GET",
            "header": [],
            "url": {
              "raw": "{{baseUrl}}/reviews/product/:productId?page=1&limit=20",
              "host": ["{{baseUrl}}"],
              "path": ["reviews", "product", ":productId"],
              "query": [
                {
                  "key": "page",
                  "value": "1"
                },
                {
                  "key": "limit",
                  "value": "20"
                }
              ],
              "variable": [
                {
                  "key": "productId",
                  "value": "{{productId}}"
                }
              ]
            }
          }
        },
        {
          "name": "Get Product Rating Stats",
          "request": {
            "method": "GET",
            "header": [],
            "url": {
              "raw": "{{baseUrl}}/reviews/product/:productId/stats",
              "host": ["{{baseUrl}}"],
              "path": ["reviews", "product", ":productId", "stats"],
              "variable": [
                {
                  "key": "productId",
                  "value": "{{productId}}"
                }
              ]
            }
          }
        }
      ]
    },
    {
      "name": "Admin",
      "item": [
        {
          "name": "Get System Statistics",
          "request": {
            "method": "GET",
            "header": [
              {
                "key": "Authorization",
                "value": "Bearer {{adminToken}}"
              }
            ],
            "url": {
              "raw": "{{baseUrl}}/admin/stats",
              "host": ["{{baseUrl}}"],
              "path": ["admin", "stats"]
            }
          }
        },
        {
          "name": "List Users",
          "request": {
            "method": "GET",
            "header": [
              {
                "key": "Authorization",
                "value": "Bearer {{adminToken}}"
              }
            ],
            "url": {
              "raw": "{{baseUrl}}/admin/users?page=1&limit=20",
              "host": ["{{baseUrl}}"],
              "path": ["admin", "users"],
              "query": [
                {
                  "key": "page",
                  "value": "1"
                },
                {
                  "key": "limit",
                  "value": "20"
                }
              ]
            }
          }
        },
        {
          "name": "Update User Role",
          "request": {
            "method": "PATCH",
            "header": [
              {
                "key": "Authorization",
                "value": "Bearer {{adminToken}}"
              },
              {
                "key": "Content-Type",
                "value": "application/json"
              }
            ],
            "body": {
              "mode": "raw",
              "raw": "{\n  \"role\": \"MANAGER\"\n}"
            },
            "url": {
              "raw": "{{baseUrl}}/admin/users/:id/role",
              "host": ["{{baseUrl}}"],
              "path": ["admin", "users", ":id", "role"],
              "variable": [
                {
                  "key": "id",
                  "value": "{{userId}}"
                }
              ]
            }
          }
        },
        {
          "name": "List Orders (Admin)",
          "request": {
            "method": "GET",
            "header": [
              {
                "key": "Authorization",
                "value": "Bearer {{adminToken}}"
              }
            ],
            "url": {
              "raw": "{{baseUrl}}/admin/orders?page=1&limit=20",
              "host": ["{{baseUrl}}"],
              "path": ["admin", "orders"],
              "query": [
                {
                  "key": "page",
                  "value": "1"
                },
                {
                  "key": "limit",
                  "value": "20"
                }
              ]
            }
          }
        }
      ]
    },
    {
      "name": "Shipping",
      "item": [
        {
          "name": "Get Shipping Rates",
          "request": {
            "method": "GET",
            "header": [
              {
                "key": "Authorization",
                "value": "Bearer {{accessToken}}"
              }
            ],
            "url": {
              "raw": "{{baseUrl}}/shipping/orders/:orderId/rates",
              "host": ["{{baseUrl}}"],
              "path": ["shipping", "orders", ":orderId", "rates"],
              "variable": [
                {
                  "key": "orderId",
                  "value": "{{orderId}}"
                }
              ]
            }
          }
        },
        {
          "name": "Create Shipment (Admin)",
          "request": {
            "method": "POST",
            "header": [
              {
                "key": "Authorization",
                "value": "Bearer {{adminToken}}"
              },
              {
                "key": "Content-Type",
                "value": "application/json"
              }
            ],
            "body": {
              "mode": "raw",
              "raw": "{\n  \"service\": \"Standard\"\n}"
            },
            "url": {
              "raw": "{{baseUrl}}/shipping/orders/:orderId/shipments",
              "host": ["{{baseUrl}}"],
              "path": ["shipping", "orders", ":orderId", "shipments"],
              "variable": [
                {
                  "key": "orderId",
                  "value": "{{orderId}}"
                }
              ]
            }
          }
        }
      ]
    }
  ]
}

